{
  "name": "MyApp Container",
  "dockerComposeFile": "../docker-compose.yml",
  "service": "dev",
  "workspaceFolder": "/app",
  "shutdownAction": "stopCompose",
  "customizations": {
    "vscode": {
      "extensions": [
        "jakebecker.elixir-ls",
        "phoenixframework.phoenix",
        "pantajoe.vscode-elixir-credo",
        "samuel-pordeus.elixir-test"
      ],
      "settings": {
        "editor.formatOnSave": true,
        "elixirLS.dialyzerEnabled": true,
        "elixirLS.fetchDeps": true,
        "elixir.credo.configFile": "../.credo.exs",
        "files.associations": {
          "*.heex": "phoenix-heex",
        },
        "[elixir]": {
          "editor.formatOnSave": true,
          "editor.defaultFormatter": "JakeBecker.elixir-ls"
        },
        "[phoenix-heex]": {
          "editor.formatOnSave": true,
          "editor.defaultFormatter": "JakeBecker.elixir-ls"
        },
      },
    }
  },
}